LICENSE
MANIFEST.in
README.md
setup.cfg
setup.py
bin/pynode-example.py
steamlink/__init__.py
steamlink/const.py
steamlink/db.py
steamlink/linkage.py
steamlink/main.py
steamlink/mqtt.py
steamlink/pynode.py
steamlink/steamlink.py
steamlink/testdata.py
steamlink/util.py
steamlink/web.py
steamlink.egg-info/PKG-INFO
steamlink.egg-info/SOURCES.txt
steamlink.egg-info/dependency_links.txt
steamlink.egg-info/entry_points.txt
steamlink.egg-info/not-zip-safe
steamlink.egg-info/requires.txt
steamlink.egg-info/top_level.txt
steamlink/html/static/custom.css
steamlink/html/static/favicon.ico
steamlink/html/static/link.svg
steamlink/html/static/main.js
steamlink/html/static/normalize.css
steamlink/html/static/skeleton.css
steamlink/html/templates/alert.html
steamlink/html/templates/form.html
steamlink/html/templates/index.html
steamlink/html/templates/index.yaml
steamlink/html/templates/log.yaml
steamlink/html/templates/map.html
steamlink/html/templates/mesh.yaml
steamlink/html/templates/navbar.html
steamlink/html/templates/navbar.yaml
steamlink/html/templates/node.yaml
steamlink/html/templates/packet.yaml
steamlink/html/templates/pie.html
steamlink/html/templates/pumps.yaml
steamlink/html/templates/table.html
steamlink/html/templates/tile.html
steamlink/html/templates/timeline.html