Metadata-Version: 1.1
Name: steamlink
Version: 0.9.2
Summary: Open-source IoT network framework running on Python 3.
Home-page: https://steamlink.net/
Author: SteamLink Authors
Author-email: info+git@steamlink.net
License: MIT License
Download-URL: https://github.com/steamlink/steamlink/archive/0.9.2.tar.gz
Keywords: iot,LoRa
Platform: any
Classifier: Intended Audience :: Developers
Classifier: License :: OSI Approved :: MIT License
Classifier: Operating System :: OS Independent
Classifier: Programming Language :: Python :: 3.6
Classifier: Topic :: Software Development :: Libraries :: Python Modules
Classifier: Topic :: Internet :: WWW/HTTP :: Dynamic Content
